funneld.py
setup.cfg
setup.py
funneld.egg-info/PKG-INFO
funneld.egg-info/SOURCES.txt
funneld.egg-info/dependency_links.txt
funneld.egg-info/entry_points.txt
funneld.egg-info/requires.txt
funneld.egg-info/top_level.txt