Metadata-Version: 1.0
Name: funneld
Version: 0.1.0
Summary: funnel ssh logins through a single system user
Home-page: https://github.com/dustinlacewell/funneld
Author: Dustin Lacewell
Author-email: dlacewell@gmail.com
License: UNKNOWN
Platform: UNKNOWN
